cdspyreadme/CDSColumn.py
cdspyreadme/MRT.template
cdspyreadme/ReadMe.template
cdspyreadme/__init__.py
cdspyreadme/bytebybyte.template
cdspyreadme/core.py
cdspyreadme/core_test.py
cdspyreadme-1.7.dist-info/licenses/LICENSE.txt
cdspyreadme-1.7.dist-info/METADATA
cdspyreadme-1.7.dist-info/WHEEL
cdspyreadme-1.7.dist-info/top_level.txt
cdspyreadme-1.7.dist-info/RECORD
