Metadata-Version: 2.4
Name: cdspyreadme
Version: 1.7
Summary: ReadMe generator package (cdspyreadme)
Author-email: "Gilles Landais (CDS)" <gilles.landais@unistra.fr>
License-Expression: BSD-3-Clause
Project-URL: Homepage, https://github.com/cds-astro/cds.pyreadme
Keywords: astronomy,CDS
Classifier: Programming Language :: Python :: 3.6
Classifier: Operating System :: OS Independent
Classifier: Intended Audience :: Science/Research
Classifier: Topic :: Scientific/Engineering :: Astronomy
Requires-Python: >=3.6
License-File: LICENSE.txt
Requires-Dist: astropy>=3.2
Requires-Dist: numpy>=1.17.2
Dynamic: license-file
